pileoffeather/__init__.py
pileoffeather/pod.py
pileoffeather/pof.py
pileoffeather-0.3.1.dist-info/LICENSE
pileoffeather-0.3.1.dist-info/METADATA
pileoffeather-0.3.1.dist-info/WHEEL
pileoffeather-0.3.1.dist-info/top_level.txt
pileoffeather-0.3.1.dist-info/RECORD
