Metadata-Version: 2.1
Name: pileoffeather
Version: 0.3.1
Summary: Lightweight and easy to use ml library for small projects, create a neural network in minutes.
Home-page: https://github.com/usedToBeTomas/pile-of-feather
Author: Daniele Tomaselli
License: MIT
Keywords: neural network,ml,ai,machine learning,simple,nn
Requires-Python: >=3.6
License-File: LICENSE
Requires-Dist: opencv-python
Requires-Dist: numpy
